pdfcli/__init__.py
pdfcli/main.py
pdfcli/commands/__init__.py
pdfcli/commands/compress.py
pdfcli/commands/convert.py
pdfcli/commands/decrypt.py
pdfcli/commands/encrypt.py
pdfcli/commands/merge.py
pdfcli/commands/reorder.py
pdfcli/commands/split.py
pdfcli/commands/trim.py
pdfcli/utils/cli_utils.py
pdfcli/utils/page_utils.py
pdfcli/utils/validators.py
simple_pdf_cli-0.2.1.dist-info/METADATA
simple_pdf_cli-0.2.1.dist-info/WHEEL
simple_pdf_cli-0.2.1.dist-info/entry_points.txt
simple_pdf_cli-0.2.1.dist-info/RECORD
