Metadata-Version: 2.4
Name: simple-pdf-cli
Version: 0.2.1
Summary: A simple CLI app for basic PDF modifications.
Project-URL: Repository, https://github.com/Falachi/simple-pdf-cli
Author: Falachi
License-Expression: MIT
Keywords: cli,compress-pdf,merge-pdf,pdf,pdf-decrypt,pdf-encrypt,pdf-split,pdf-to-image,pdf-tools,pdf-trim
Classifier: Programming Language :: Python :: 3
Classifier: Programming Language :: Python :: 3 :: Only
Classifier: Programming Language :: Python :: 3.10
Classifier: Programming Language :: Python :: 3.11
Classifier: Programming Language :: Python :: 3.12
Requires-Python: >=3.10
Requires-Dist: cryptography>=46.0.0
Requires-Dist: natsort==8.4.0
Requires-Dist: pdf2image>=1.17.0
Requires-Dist: pillow>=12.0.0
Requires-Dist: pypdf>=6.3.0
Requires-Dist: rich>=14.2.0
Requires-Dist: typer>=0.20.0
Provides-Extra: dev
Requires-Dist: pytest; extra == 'dev'
